edp_redy/__init__.py
edp_redy/session.py
edp_redy-0.0.3.dist-info/METADATA
edp_redy-0.0.3.dist-info/RECORD
edp_redy-0.0.3.dist-info/WHEEL
edp_redy-0.0.3.dist-info/top_level.txt
